{
  "kind": "collectionType",
  "collectionName": "editorials",
  "info": {
    "singularName": "editorial",
    "pluralName": "editorials",
    "displayName": "Editorial Article",
    "description": "Opinion, analysis and special editorial content."
  },
  "options": {
    "draftAndPublish": true
  },
  "indexes": [
    {
      "name": "editorials_slug_idx",
      "columns": [
        "slug"
      ]
    },
    {
      "name": "editorials_isEditorsPick_idx",
      "columns": [
        "is_editors_pick"
      ]
    },
    {
      "name": "editorials_views_idx",
      "columns": [
        "views"
      ]
    },
    {
      "name": "editorials_scheduledAt_idx",
      "columns": [
        "scheduled_at"
      ]
    },
    {
      "name": "editorials_publishedAt_idx",
      "columns": [
        "published_at"
      ]
    },
    {
      "name": "editorials_heroPriority_idx",
      "columns": [
        "hero_priority"
      ]
    }
  ],
  "attributes": {
    "title": {
      "type": "string",
      "required": true,
      "maxLength": 200
    },
    "titleHindi": {
      "type": "string",
      "maxLength": 200
    },
    "slug": {
      "type": "uid",
      "targetField": "title",
      "required": true,
      "unique": true
    },
    "excerpt": {
      "type": "text"
    },
    "excerptHindi": {
      "type": "text"
    },
    "content": {
      "type": "richtext",
      "required": true
    },
    "contentHindi": {
      "type": "richtext"
    },
    "image": {
      "type": "media",
      "multiple": false,
      "allowedTypes": [
        "images"
      ]
    },
    "readTime": {
      "type": "string",
      "maxLength": 30
    },
    "views": {
      "type": "integer",
      "default": 0
    },
    "seoTitle": {
      "type": "string",
      "maxLength": 60
    },
    "seoDescription": {
      "type": "text",
      "maxLength": 160
    },
    "seoOverride": {
      "type": "boolean",
      "default": false
    },
    "canonicalUrl": {
      "type": "string"
    },
    "newsKeywords": {
      "type": "text"
    },
    "schemaJson": {
      "type": "json"
    },
    "isEditorsPick": {
      "type": "boolean",
      "default": false
    },
    "heroPriority": {
      "type": "integer"
    },
    "scheduledAt": {
      "type": "datetime"
    },
    "category": {
      "type": "relation",
      "relation": "manyToOne",
      "target": "api::category.category",
      "inversedBy": "editorials",
      "required": true
    },
    "author": {
      "type": "relation",
      "relation": "manyToOne",
      "target": "api::author.author",
      "inversedBy": "editorials",
      "required": true
    }
  }
}
